pywsdp/__init__.py
pywsdp/base/__init__.py
pywsdp/base/exceptions.py
pywsdp/base/logger.py
pywsdp/clients/__init__.py
pywsdp/clients/factory.py
pywsdp/clients/helpers/__init__.py
pywsdp/clients/helpers/ctiOS/__init__.py
pywsdp/clients/helpers/generujCenoveUdajeDleKu/__init__.py
pywsdp/modules/__init__.py
pywsdp/modules/CtiOS/__init__.py
pywsdp/modules/CtiOS/formats.py
pywsdp/modules/CtiOS/helpers.py
pywsdp/modules/GenerujCenoveUdajeDleKu/__init__.py
pywsdp/modules/SpravujSestavy/__init__.py
tests/__init__.py
tests/test.py
pywsdp-2.2.0.dist-info/LICENSE
pywsdp-2.2.0.dist-info/METADATA
pywsdp-2.2.0.dist-info/WHEEL
pywsdp-2.2.0.dist-info/top_level.txt
pywsdp-2.2.0.dist-info/RECORD
