Metadata-Version: 2.1
Name: pywsdp
Version: 2.2.0
Summary: PyWSDP Python package
Home-page: https://github.com/ctu-geoforall-lab/pywsdp
Author: Linda Kladivova
Author-email: lindakladivova@gmail.com
Classifier: Programming Language :: Python :: 3
Classifier: License :: OSI Approved :: MIT License
Classifier: Operating System :: OS Independent
Requires-Python: >=3.7
License-File: LICENSE
Requires-Dist: zeep (>=4.1.0)
